voltfpipe/__init__.py
voltfpipe/cli.py
voltfpipe/core.py
voltfpipe-0.1.0.dist-info/entry_points.txt
voltfpipe-0.1.0.dist-info/WHEEL
voltfpipe-0.1.0.dist-info/METADATA
voltfpipe-0.1.0.dist-info/RECORD
